LICENSE
MANIFEST.in
README.rst
pyproject.toml
setup.cfg
setup.py
django_kafka_event_log.egg-info/PKG-INFO
django_kafka_event_log.egg-info/SOURCES.txt
django_kafka_event_log.egg-info/dependency_links.txt
django_kafka_event_log.egg-info/top_level.txt
events/__init__.py
events/apps.py
events/models.py
events/utils.py
events/common/__init__.py
events/common/base_service_mixin.py
events/migrations/0001_initial.py
events/migrations/__init__.py
events/tests/__init__.py
events/tests/test_utils.py
events/tests/models/__init__.py
events/tests/models/sample.py
events/tests/serializers/__init__.py
events/tests/serializers/sample_serializer.py