Metadata-Version: 2.1
Name: django-kafka-event-log
Version: 0.1.6
Summary: A Django app to store an event and publish the event to Kafka
Home-page: https://github.com/DiagVN/django-kafka-event-log
Author: Diag
Author-email: ngu.truong@diag.vn
License: UNKNOWN
Keywords: django kafka event-log
Platform: UNKNOWN
Classifier: Development Status :: 5 - Production/Stable
Classifier: Intended Audience :: Developers
Classifier: Intended Audience :: System Administrators
Classifier: License :: OSI Approved :: MIT License
Classifier: Operating System :: OS Independent
Classifier: Topic :: Software Development :: Build Tools
Classifier: Topic :: Software Development :: Libraries :: Python Modules
Classifier: Topic :: Internet
Classifier: Framework :: Django
Classifier: Programming Language :: Python :: 3
Classifier: Programming Language :: Python :: 3 :: Only
Requires-Python: >=3
License-File: LICENSE
